fastforge/__init__.py
fastforge/cli.py
fastforge-0.0.2.dist-info/LICENSE
fastforge-0.0.2.dist-info/METADATA
fastforge-0.0.2.dist-info/WHEEL
fastforge-0.0.2.dist-info/entry_points.txt
fastforge-0.0.2.dist-info/top_level.txt
fastforge-0.0.2.dist-info/RECORD
