Metadata-Version: 2.1
Name: fastforge
Version: 0.0.2
Summary: A FastAPI utility CLI
Home-page: https://github.com/soham901/fastforge
Author: Soham Sagathiya
Author-email: soham.saga@gmail.com
License: MIT
Classifier: Programming Language :: Python :: 3
Classifier: Programming Language :: Python :: 3.8
Classifier: Programming Language :: Python :: 3.9
Classifier: License :: OSI Approved :: MIT License
Classifier: Operating System :: OS Independent
Requires-Python: >=3.8
License-File: LICENSE
Requires-Dist: click
Requires-Dist: fastapi
